encode_mcp_server/__init__.py
encode_mcp_server/server.py
encode_mcp_server-0.1.0.dist-info/METADATA
encode_mcp_server-0.1.0.dist-info/WHEEL
encode_mcp_server-0.1.0.dist-info/entry_points.txt
encode_mcp_server-0.1.0.dist-info/RECORD
